multi_clipboard/__init__.py
multi_clipboard/__main__.py
multi_clipboard/clipboard.py
multi_clipboard/db.py
multi_clipboard/listener.py
multi_clipboard/ui.py
multi_clipboard/utils.py
multi_clipboard/images/add.png
multi_clipboard/images/close.png
multi_clipboard/images/delete.png
multi_clipboard/images/settings.png
multi_clipboard-1.3.0.dist-info/METADATA
multi_clipboard-1.3.0.dist-info/RECORD
multi_clipboard-1.3.0.dist-info/WHEEL
multi_clipboard-1.3.0.dist-info/entry_points.txt
multi_clipboard-1.3.0.dist-info/top_level.txt
