Metadata-Version: 2.1
Name: multi-clipboard
Version: 1.3.0
Summary: Switch clipboard contents using a simple GUI
Home-page: https://github.com/brentvollebregt/mutli-clipboard
Author: Brent Vollebregt
Author-email: brent@nitratine.net
License: MIT
Keywords: gui,clipboard
Platform: UNKNOWN
Classifier: License :: OSI Approved :: MIT License
Classifier: Programming Language :: Python
Classifier: Programming Language :: Python :: 3.5
Classifier: Programming Language :: Python :: 3.6
Classifier: Programming Language :: Python :: 3.7
Classifier: Operating System :: Microsoft :: Windows
Requires-Python: >=3.5
Requires-Dist: pywin32
Requires-Dist: PyQt5
Requires-Dist: Pillow
Requires-Dist: pynput
